borderline.py
borderline-0.3.0.dist-info/LICENSE
borderline-0.3.0.dist-info/WHEEL
borderline-0.3.0.dist-info/METADATA
borderline-0.3.0.dist-info/RECORD
